Workbook

Sheet Itinerary Form
A1: TRAVEL ITINERARY FORM
A2: Instructions: Please complete all applicable fields to the best of your ability. Fields shaded in gray are auto-calculated fields and do not need to be completed.
A5: TRAVELER AND GENERAL INFORMATION
B6: Traveler Name | C6: Timothy Stranske | E6: Destination Zip Code | G6: 94105 | H6: =IFERROR(_xlfn.CONCAT(VLOOKUP(G6,Locations!A:F,4,FALSE()),", ",VLOOKUP(G6,Locations!A:F,6,FALSE())),"City / State") -> San Francisco, California | K6: Event/Meeting Date(s): | M6: 1/14-1/15
K7: Departure Date | M7: 46035
B8: Purpose of Trip | K8: Return Date
C9: (Attach conference or seminar summary agenda.)
B10: □ | C10: I plan to reserve additional days for me prior to or following my business travel for my personal use. | K10: Event Registration Costs | M10: 0
A13: AIRFARE AND FLIGHT RELATED EXPENSES
B14: Departure City/Airport: | H14: Return City/Airport:
B16: Preferred flight(s) departing | D16: Carrier Name & Flight | H16: Departure time | J16: Arrival time | L16: Round trip cost
B17: Preferred flight(s) returning | D17: Carrier Name & Flight | H17: Departure time | J17: Arrival time | M17: 0
B18: Note: The prices noted for flights are at the time of research and may have varied from the time of research to the time they were booked.
B20: Lowest cost round trip ticket available: | E20: 0 | I20: Airport Parking Estimate
B21: (Attach print out or screen shot of the price of the lowest possible airline cost for your trip.) | I21: # Days | K21: =+$M$8-$M$7 -> -46035
I22: Daily Rate | K22: 0 | M22: Total Flight Expenses | O22: =SUM(M17,C23,F23,K23) -> 0
B23: Airport Hotel Cost | C23: 0 | E23: Other Costs (describe) | F23: 0 | I23: Parking Cost | K23: =K21*K22 -> 0
B27: □ | C27: By checking this box, I am affirming that the round trip cost of my preferred flight at the time of my research was within $200 of the lowest price flight as noted above.
B28: □ | C28: My meeting starts on Monday or ends on Friday and I am willing or prefer to stay over an extra night because a reduced airfare produces a savings (net of hotel and other related expenses).
B29: □ | C29: I plan to book a hotel reservation (in St. Louis or Kansas City) the night prior to or night of my return in order to obtain a lower airfare rate or avoid early morning or late night travel.
B30: □ | C30: I request to fly out of Columbia and the airfare exceeds the $200 lowest cost threshold; however, I can document other travel savings to offset the difference in airfare costs (explain below).
B32: Additional Information:
A35: DESTINATION HOTEL
B36: Name | J36: Cost Per Night | K36: 0 | M36: Number of Nights | O36: =+$M$8-$M$7 -> -46035
K37: (excludes taxes) | M37: (business travel only)
B38: Address | G38: City/State
M39: Total Hotel Costs | O39: =K36*O36 -> 0
B40: □ | C40: I am attending a conference and this is the conference hotel.
B41: □ | C41: By checking this box, I am affirming that the prices of other hotels in the vicinity of the meeting were reviewed prior to selecting this hotel. Personal safety, proximity to meeting, and transportation issues were factors for this hotel decision if the lowest cost hotel was not selected.
K43: Additional Information
B44: Comparable Hotels in the vicinity of the meeting/conference
B45: Name | G45: Cost Per Night
B46: Name | G46: Cost Per Night
A49: MEAL & INCIDENTAL EXPENSE (M&IE)
B50: Destination City & State | F50: Meal Per Diem Rates and Estimated Reimburseable Meal Counts | K50: Incidental Expense | N50: Total M&I | O50: =I55+M54 -> -4235220
G51: Per Diem Rate | H51: Count | I51: Total
C52: =H6 -> San Francisco, California | F52: Breakfast | G52: =IFERROR(VLOOKUP(D54,'Per Meal Rates by Total'!A5:D10,2,FALSE()),) -> 23 | H52: =+$M$8-$M$7 -> -46035 | I52: =G52*H52 -> -1058805 | K52: Number of Nights | M52: =O36 -> -46035
F53: Lunch | G53: =IFERROR(VLOOKUP(D54,'Per Meal Rates by Total'!A5:D10,3,FALSE()),) -> 26 | H53: =+$M$8-$M$7 -> -46035 | I53: =G53*H53 -> -1196910 | K53: Incidental Rate Per Day | M53: 5
B54: Federal M&IE Total | D54: =IF(H6<>"City / State",VLOOKUP(G6,'Federal Meal Total Rates'!A:U,21,FALSE()),) -> 92 | F54: Dinner | G54: =IFERROR(VLOOKUP(D54,'Per Meal Rates by Total'!A5:D10,4,FALSE()),) -> 38 | H54: =+$M$8-$M$7 -> -46035 | I54: =G54*H54 -> -1749330 | K54: Total Incidental Expenses | M54: =M52*M53 -> -230175
F55: Total Meal Estimate | I55: =SUM(I52:I54) -> -4005045
A58: AIR TRAVEL VERSUS DRIVING COST COMPARISON
B59: □ | C59: I plan to drive instead of fly and understand that I will only be reimbursed for the lesser of the below cost comparison. (Complete the requested cost comparison information if you intend to take your personal vehicle instead of flying.)
B61: Driving Option | D61: Miles | E61: Cost | G61: Air Travel Option | I61: Cost | K61: Additional Information
B62: Business Mileage | E62: =D62*C74 -> 0 | G62: Airfare | K62: Explain any expenses categorized as 'other' and insert additional details here.
B63: Destination Parking | G63: Mileage | I63: 0
B64: Other | G64: Airport Parking
A65: (complete only if you plan to drive instead of fly) | B65: TOTAL | E65: =SUM(E62:E64) -> 0 | G65: Ground Transportation
G66: Other
G67: TOTAL | I67: =SUM(I62:I66) -> 0
A70: GROUND TRANSPORTATION
B71: Mileage Reimbursement Calculator | E71: Rental Vehicle Estimate | K71: Ground Transporation Summary (check all options planned)
M72: Planned? | N72: Cost Estimate
B73: Miles | E73: Rental Company | H73: Vehicle Class Size | I73: Mid-size sedan (default) | K73: MOSERS Vehicle | M73: □ | N73: n/a
B74: Rate/Mile | C74: 0.725 | E74: # of Days | G74: =+$M$8-$M$7 -> -46035 | H74: Daily Rate | I74: 0 | K74: Mileage Reimbursement | M74: □ | N74: =C75 -> 0
B75: TOTAL | C75: =C73*C74 -> 0 | K75: Rideshare or Taxi Services | M75: □ | N75: 0
E76: Reason for Rental | K76: Shuttle | M76: □ | N76: 0
K77: Rental Vehicle | M77: □ | N77: =G74*I74 -> 0
K78: Total Ground Transporation Costs | N78: =SUM(N74:N77) -> 0
A81: EXPENSES PAID BY MOSERS
I82: Additional Information
B83: □ | C83: Some trip expenses will be paid directly by MOSERS. Describe in the box provided. | I83: Describe expenses paid for directly by MOSERS (include item name and cost).
B84: □ | C84: I intend to request a cash advance. Provide amount in the box provided.
A88: EXPENSES PAID BY A THIRD PARTY
F89: Estimated Value | I89: Additional Information
B90: □ | C90: Hotel expenses to be paid by a third party. | F90: 0 | I90: Provide additional information here.
B91: □ | C91: Airfare expenses to be paid by a third party. | F91: 0
B93: Third Party Name
A96: TOTAL ESTIMATED TRIP COSTS
C97: Meals & Incidential Expenses | G97: =O50 -> -4235220 | I97: Additional Information
C98: Flight Expenses | G98: =O22 -> 0
C99: Destination Hotel | G99: =O39 -> 0
C100: Ground Transportation | G100: =N78 -> 0
C101: Event Registation | G101: =M10 -> 0
C102: Other (not included above, describe) | G102: 0
C103: Total Trip Costs | G103: =SUM(G97:G102) -> -4235220
A106: REQUESTOR AFFIRMATION AND SIGNATURE
B107: □ | C107: By checking this box, I have confirmed that this travel/conference/employee development is in my section's budget.
B109: I understand that I will not make travel arrangements or obligate MOSERS for any travel costs until this form is approved. I attest that all of the information contained on this form is accurate or my best estimation of the anticipated travel costs for my trip. I have reviewed the Business Travel and Reimbursement Policy in the MOSERS Handbook and understand I will be reimbursed according to those guidelines.
M110: Requestor signature and date
A113: APPROVALS
C115: Manager Approval | F115: I have reviewed the reason to make this trip and approve the travel.
M116: Manager signature and date
C118: Executive Project Coordinator | F118: I have reviewed this itinerary in accordance with the Business Travel and Reimbursement Policy.
M119: Executive Project Coordinator signature and date

Sheet Locations
A1: zip | B1: lat | C1: lng | D1: city | E1: state_id | F1: state_name
A2: 601 | D2: Adjuntas | F2: Puerto Rico
A3: 602 | D3: Aguada | F3: Puerto Rico
A4: 603 | D4: Aguadilla | F4: Puerto Rico
A5: 606 | D5: Maricao | F5: Puerto Rico
A6: 610 | D6: Anasco | F6: Puerto Rico
A7: 611 | D7: Angeles | F7: Puerto Rico
A8: 612 | D8: Arecibo | F8: Puerto Rico
A9: 616 | D9: Bajadero | F9: Puerto Rico
A10: 617 | D10: Barceloneta | F10: Puerto Rico
A11: 622 | D11: Boqueron | F11: Puerto Rico
A12: 623 | D12: Cabo Rojo | F12: Puerto Rico
A13: 624 | D13: Penuelas | F13: Puerto Rico
... A33788: 99929 | D33788: Wrangell | F33788: Alaska

Sheet Federal Meal Total Rates
A1: Postal code | B1: DestinationID | C1: Name | D1: County | E1: LocationDefined | F1: State | G1: Zip | H1: FiscalYear | I1: Oct | J1: Nov | K1: Dec | L1: Jan | M1: Feb | N1: Mar | O1: Apr | P1: May | Q1: Jun | R1: Jul | S1: Aug | T1: Sep | U1: Meals and & Incidental Expenses Total
A2: 501 | U2: 86
A3: 544 | U3: 86
A4: 1001 | U4: 74
A5: 1002 | U5: 80
A6: 1003 | U6: 80
A7: 1004 | U7: 80
A8: 1005 | U8: 80
A9: 1007 | U9: 80
A10: 1008 | U10: 74
A11: 1009 | U11: 74
A12: 1010 | U12: 74
A13: 1011 | U13: 80
... A42359: 99403 | U42359: 68

Sheet Per Meal Rates by Total
A1: Federal M&IE Breakdown by Meal, Federal FY 2025
A2: Last Reviewed: 9/16/2024
A4: M&IE Total | B4: Breakfast | C4: Lunch | D4: Dinner | E4: Incidental
E5: Expenses
A6: 68 | B6: 16 | C6: 19 | D6: 28 | E6: 5
A7: 74 | B7: 18 | C7: 20 | D7: 31 | E7: 5
A8: 80 | B8: 20 | C8: 22 | D8: 33 | E8: 5
A9: 86 | B9: 22 | C9: 23 | D9: 36 | E9: 5
A10: 92 | B10: 23 | C10: 26 | D10: 38 | E10: 5

Sheet Sheet2
A1: □
A2: ✓
